[
    {
        "id": "identity_0",
        "conversations": [
            {
                "from": "user",
                "value": "在法学门类一级学科中共党史党建学下设了几个二级学科？"
            },
            {
                "from": "assistant",
                "value": "法学门类一级学科中共党史党建学下设了4个二级学科。"
            }
        ],
        "fact": "中共党史党建学成为法学门类一级学科后，相关部门确立了4个二级学科，即中共党史党建学理论、中国共产党历史、党的领导和党的建设、党务工作理论与实践。",
        "file_name": "中共党史党建学的本体论、认识论和方法论.txt"
    },
    {
        "id": "identity_1",
        "conversations": [
            {
                "from": "user",
                "value": "在中共党史党建学成为法学门类一级学科后，相关部门设立了几个二级学科？"
            },
            {
                "from": "assistant",
                "value": "在中共党史党建学成为法学门类一级学科后，相关部门设立了4个二级学科。"
            }
        ],
        "fact": "中共党史党建学成为法学门类一级学科后，相关部门确立了4个二级学科，即中共党史党建学理论、中国共产党历史、党的领导和党的建设、党务工作理论与实践。",
        "file_name": "中共党史党建学的本体论、认识论和方法论.txt"
    },
    {
        "id": "identity_2",
        "conversations": [
            {
                "from": "user",
                "value": "中共党史党建学成为法学门类一级学科后，相关部门确立了哪些二级学科？"
            },
            {
                "from": "assistant",
                "value": "中共党史党建学成为法学门类一级学科后，相关部门确立了4个二级学科，包括中共党史党建学理论、中国共产党历史、党的领导和党的建设以及党务工作理论与实践。"
            }
        ],
        "fact": "中共党史党建学成为法学门类一级学科后，相关部门确立了4个二级学科，即中共党史党建学理论、中国共产党历史、党的领导和党的建设、党务工作理论与实践。",
        "file_name": "中共党史党建学的本体论、认识论和方法论.txt"
    },
    {
        "id": "identity_3",
        "conversations": [
            {
                "from": "user",
                "value": "请列举中共党史党建学成为法学门类一级学科后设立的四个二级学科。"
            },
            {
                "from": "assistant",
                "value": "中共党史党建学成为法学门类一级学科后设立的四个二级学科是：中共党史与党的建设、中国共产党历史、党的领导与党的建设以及党政工作理论与实践。"
            }
        ],
        "fact": "中共党史党建学成为法学门类一级学科后，相关部门确立了4个二级学科，即中共党史党建学理论、中国共产党历史、党的领导和党的建设、党务工作理论与实践。",
        "file_name": "中共党史党建学的本体论、认识论和方法论.txt"
    },
    {
        "id": "identity_4",
        "conversations": [
            {
                "from": "user",
                "value": "中共党史党建学成为法学门类一级学科后，相关部门设立了几个二级学科？"
            },
            {
                "from": "assistant",
                "value": "中共党史党建学成为法学门类一级学科后，相关部门设立了4个二级学科。"
            }
        ],
        "fact": "中共党史党建学成为法学门类一级学科后，相关部门确立了4个二级学科，即中共党史党建学理论、中国共产党历史、党的领导和党的建设、党务工作理论与实践。",
        "file_name": "中共党史党建学的本体论、认识论和方法论.txt"
    },
    {
        "id": "identity_5",
        "conversations": [
            {
                "from": "user",
                "value": "在中共党史党建学成为法学门类一级学科后，相关部门确立了哪些二级学科？"
            },
            {
                "from": "assistant",
                "value": "在中共党史党建学成为法学门类一级学科后，相关部门确立了4个二级学科，包括中共党史党建学理论、中国共产党历史、党的领导和党的建设以及党务工作理论与实践。"
            }
        ],
        "fact": "中共党史党建学成为法学门类一级学科后，相关部门确立了4个二级学科，即中共党史党建学理论、中国共产党历史、党的领导和党的建设、党务工作理论与实践。",
        "file_name": "中共党史党建学的本体论、认识论和方法论.txt"
    },
    {
        "id": "identity_6",
        "conversations": [
            {
                "from": "user",
                "value": "请问中共党史党建学成为法学门类一级学科后，下设了多少个二级学科？"
            },
            {
                "from": "assistant",
                "value": "中共党史党建学成为法学门类一级学科后，下设了4个二级学科。"
            }
        ],
        "fact": "中共党史党建学成为法学门类一级学科后，相关部门确立了4个二级学科，即中共党史党建学理论、中国共产党历史、党的领导和党的建设、党务工作理论与实践。",
        "file_name": "中共党史党建学的本体论、认识论和方法论.txt"
    },
    {
        "id": "identity_7",
        "conversations": [
            {
                "from": "user",
                "value": "能否列举一下中共历史与党的建设学科下设有哪些具体的研究方向？"
            },
            {
                "from": "assistant",
                "value": "当然可以。该学科下设的研究方向包括：马克思主义中国化研究、思想政治教育、科学社会主义与国际共产主义运动等。"
            }
        ],
        "fact": "中共党史党建学成为法学门类一级学科后，相关部门确立了4个二级学科，即中共党史党建学理论、中国共产党历史、党的领导和党的建设、党务工作理论与实践。",
        "file_name": "中共党史党建学的本体论、认识论和方法论.txt"
    },
    {
        "id": "identity_8",
        "conversations": [
            {
                "from": "user",
                "value": "在中国共产党的历史上，我们主要研究和探讨的是什么？"
            },
            {
                "from": "assistant",
                "value": "我们主要研究和探讨的是中国共产党百余年来的奋斗历程、取得的重大成就、积累的基本经验以及历史发展的规律。"
            }
        ],
        "fact": "中国共产党历史旨在考察和研究中国共产党百余年奋斗的历史进程、重大成就、基本经验和历史规律。",
        "file_name": "中共党史党建学的本体论、认识论和方法论.txt"
    },
    {
        "id": "identity_9",
        "conversations": [
            {
                "from": "user",
                "value": "请简要介绍一下中国共产党历史的研究内容。"
            },
            {
                "from": "assistant",
                "value": "中国共产党历史的研究内容主要包括其奋斗的历史进程、取得的重大成就、积累的基本经验以及对历史发展规律的探索。"
            }
        ],
        "fact": "中国共产党历史旨在考察和研究中国共产党百余年奋斗的历史进程、重大成就、基本经验和历史规律。",
        "file_name": "中共党史党建学的本体论、认识论和方法论.txt"
    },
    {
        "id": "identity_10",
        "conversations": [
            {
                "from": "user",
                "value": "能否概括一下中国共产党历史的主要研究方向？"
            },
            {
                "from": "assistant",
                "value": "可以，其主要研究方向包括：考察和研究党的奋斗历程，分析其重大成就，总结基本经验，探索历史发展规律。"
            }
        ],
        "fact": "中国共产党历史旨在考察和研究中国共产党百余年奋斗的历史进程、重大成就、基本经验和历史规律。",
        "file_name": "中共党史党建学的本体论、认识论和方法论.txt"
    },
    {
        "id": "identity_11",
        "conversations": [
            {
                "from": "user",
                "value": "在中国共产党的历史上，有哪些重要的里程碑事件？"
            },
            {
                "from": "assistant",
                "value": "中国共产党的历史上有许多重要的里程碑事件，如1921年中共一大的召开标志着中国共产党的成立，1949年新中国成立标志着中国人民从此站起来了，以及改革开放以来中国经济的快速发展等。"
            }
        ],
        "fact": "中国共产党历史旨在考察和研究中国共产党百余年奋斗的历史进程、重大成就、基本经验和历史规律。",
        "file_name": "中共党史党建学的本体论、认识论和方法论.txt"
    },
    {
        "id": "identity_12",
        "conversations": [
            {
                "from": "user",
                "value": "习近平新时代中国特色社会主义思想的核心内容是什么？"
            },
            {
                "from": "assistant",
                "value": "习近平新时代中国特色社会主义思想的核心内容是“八个明确”和“十四个坚持”。它涵盖了新时代坚持和发展什么样的中国特色社会主义、怎样坚持和发展中国特色社会主义这个重大时代课题。"
            }
        ],
        "fact": "中国共产党历史旨在考察和研究中国共产党百余年奋斗的历史进程、重大成就、基本经验和历史规律。",
        "file_name": "中共党史党建学的本体论、认识论和方法论.txt"
    },
    {
        "id": "identity_13",
        "conversations": [
            {
                "from": "user",
                "value": "在党的十九大报告中，提出了哪些新的重要论断和战略部署？"
            },
            {
                "from": "assistant",
                "value": "党的十九大报告提出了许多新的重要论断和战略部署，如“中国特色社会主义进入了新时代”、“我国社会主要矛盾已经转化为人民日益增长的美好生活需要和不平衡不充分的发展之间的矛盾”、“实施乡村振兴战略”、“建设现代化经济体系”等。"
            }
        ],
        "fact": "中国共产党历史旨在考察和研究中国共产党百余年奋斗的历史进程、重大成就、基本经验和历史规律。",
        "file_name": "中共党史党建学的本体论、认识论和方法论.txt"
    },
    {
        "id": "identity_14",
        "conversations": [
            {
                "from": "user",
                "value": "请简要介绍一下中国共产党历史的主要目的。"
            },
            {
                "from": "assistant",
                "value": "中国共产党历史的主要目的是考察和研究其百余年奋斗的历史进程、重大成就、基本经验和历史规律。"
            }
        ],
        "fact": "中国共产党历史旨在考察和研究中国共产党百余年奋斗的历史进程、重大成就、基本经验和历史规律。",
        "file_name": "中共党史党建学的本体论、认识论和方法论.txt"
    },
    {
        "id": "identity_15",
        "conversations": [
            {
                "from": "user",
                "value": "中国共产党在历史上有哪些重大成就？"
            },
            {
                "from": "assistant",
                "value": "中国共产党在历史上取得了许多重大成就，包括领导人民推翻了帝国主义、封建主义和官僚资本主义的统治，建立了新中国；完成了社会主义革命，确立了社会主义制度；实行改革开放政策，开创了中国特色社会主义道路等。"
            }
        ],
        "fact": "中国共产党历史旨在考察和研究中国共产党百余年奋斗的历史进程、重大成就、基本经验和历史规律。",
        "file_name": "中共党史党建学的本体论、认识论和方法论.txt"
    },
    {
        "id": "identity_16",
        "conversations": [
            {
                "from": "user",
                "value": "研究中国共产党历史有何意义？"
            },
            {
                "from": "assistant",
                "value": "研究中国共产党历史具有重要意义，可以帮助我们了解党的奋斗历程和光辉业绩，从中汲取智慧和力量；可以帮助我们更好地理解党的基本理论、基本路线、基本方略；可以为我们提供宝贵的经验教训，指导当前的实践。"
            }
        ],
        "fact": "中国共产党历史旨在考察和研究中国共产党百余年奋斗的历史进程、重大成就、基本经验和历史规律。",
        "file_name": "中共党史党建学的本体论、认识论和方法论.txt"
    },
    {
        "id": "identity_17",
        "conversations": [
            {
                "from": "user",
                "value": "在党的领导和建设中，我们主要关注哪些重大理论和实践问题？"
            },
            {
                "from": "assistant",
                "value": "我们主要关注坚持和加强党的全面领导的重大理论和实践问题，以及党自身建设的根本目的、基本方针、战略布局、重点任务和实践要求等。"
            }
        ],
        "fact": "党的领导和党的建设旨在研究坚持和加强党的全面领导的重大理论和实践问题，以及党自身建设的根本目的、基本方针、战略布局、重点任务、实践要求等。",
        "file_name": "中共党史党建学的本体论、认识论和方法论.txt"
    },
    {
        "id": "identity_18",
        "conversations": [
            {
                "from": "user",
                "value": "请简要介绍一下党的领导和建设的研究内容。"
            },
            {
                "from": "assistant",
                "value": "我们的研究方向主要包括坚持和加强党的全面领导的重大理论和实践问题，以及党自身建设的根本目的、基本方针、战略布局、重点任务和实践要求等。"
            }
        ],
        "fact": "党的领导和党的建设旨在研究坚持和加强党的全面领导的重大理论和实践问题，以及党自身建设的根本目的、基本方针、战略布局、重点任务、实践要求等。",
        "file_name": "中共党史党建学的本体论、认识论和方法论.txt"
    },
    {
        "id": "identity_19",
        "conversations": [
            {
                "from": "user",
                "value": "能否详细说明一下党的领导和建设的研究重点？"
            },
            {
                "from": "assistant",
                "value": "我们的研究重点包括坚持和加强党的全面领导的重大理论和实践问题，以及党自身建设的根本目的、基本方针、战略布局、重点任务和实践要求等方面。"
            }
        ],
        "fact": "党的领导和党的建设旨在研究坚持和加强党的全面领导的重大理论和实践问题，以及党自身建设的根本目的、基本方针、战略布局、重点任务、实践要求等。",
        "file_name": "中共党史党建学的本体论、认识论和方法论.txt"
    },
    {
        "id": "identity_20",
        "conversations": [
            {
                "from": "user",
                "value": "在党的领导和建设中，有哪些重大理论和实践问题需要研究？"
            },
            {
                "from": "assistant",
                "value": "在党的领导和建设中，需要研究的重大理论和实践问题包括坚持和加强党的全面领导的相关内容，以及党自身建设的根本目的、基本方针、战略布局、重点任务和实践要求等。"
            }
        ],
        "fact": "党的领导和党的建设旨在研究坚持和加强党的全面领导的重大理论和实践问题，以及党自身建设的根本目的、基本方针、战略布局、重点任务、实践要求等。",
        "file_name": "中共党史党建学的本体论、认识论和方法论.txt"
    },
    {
        "id": "identity_21",
        "conversations": [
            {
                "from": "user",
                "value": "请简要阐述党自身建设的根本目的。"
            },
            {
                "from": "assistant",
                "value": "党自身建设的根本目的在于确保党始终成为中国特色社会主义事业的坚强领导核心，为实现中华民族伟大复兴的中国梦提供有力保障。"
            }
        ],
        "fact": "党的领导和党的建设旨在研究坚持和加强党的全面领导的重大理论和实践问题，以及党自身建设的根本目的、基本方针、战略布局、重点任务、实践要求等。",
        "file_name": "中共党史党建学的本体论、认识论和方法论.txt"
    },
    {
        "id": "identity_22",
        "conversations": [
            {
                "from": "user",
                "value": "在党的建设中，有哪些基本方针需要遵循？"
            },
            {
                "from": "assistant",
                "value": "在党的建设中，需要遵循的基本方针包括坚持党要管党、从严治党，全面推进党的政治建设、思想建设、组织建设、作风建设、纪律建设，把制度建设贯穿其中。"
            }
        ],
        "fact": "党的领导和党的建设旨在研究坚持和加强党的全面领导的重大理论和实践问题，以及党自身建设的根本目的、基本方针、战略布局、重点任务、实践要求等。",
        "file_name": "中共党史党建学的本体论、认识论和方法论.txt"
    },
    {
        "id": "identity_23",
        "conversations": [
            {
                "from": "user",
                "value": "在党的领导和建设中，有哪些重大理论和实践问题需要研究？"
            },
            {
                "from": "assistant",
                "value": "在党的领导和建设中，需要研究的重大理论和实践问题包括坚持和加强党的全面领导的相关内容，以及党自身建设的根本目的、基本方针、战略布局、重点任务和实践要求等。"
            }
        ],
        "fact": "党的领导和党的建设旨在研究坚持和加强党的全面领导的重大理论和实践问题，以及党自身建设的根本目的、基本方针、战略布局、重点任务、实践要求等。",
        "file_name": "中共党史党建学的本体论、认识论和方法论.txt"
    },
    {
        "id": "identity_24",
        "conversations": [
            {
                "from": "user",
                "value": "请简要介绍一下党自身建设的根本目的。"
            },
            {
                "from": "assistant",
                "value": "党自身建设的根本目的在于确保党始终成为中国特色社会主义事业的坚强领导核心，为实现中华民族伟大复兴的中国梦提供有力保证。"
            }
        ],
        "fact": "党的领导和党的建设旨在研究坚持和加强党的全面领导的重大理论和实践问题，以及党自身建设的根本目的、基本方针、战略布局、重点任务、实践要求等。",
        "file_name": "中共党史党建学的本体论、认识论和方法论.txt"
    },
    {
        "id": "identity_25",
        "conversations": [
            {
                "from": "user",
                "value": "在党的建设中，有哪些基本方针需要遵循？"
            },
            {
                "from": "assistant",
                "value": "在党的建设中，需要遵循的基本方针包括坚持党要管党、从严治党，全面推进党的政治建设、思想建设、组织建设、作风建设、纪律建设，把制度建设贯穿其中。"
            }
        ],
        "fact": "党的领导和党的建设旨在研究坚持和加强党的全面领导的重大理论和实践问题，以及党自身建设的根本目的、基本方针、战略布局、重点任务、实践要求等。",
        "file_name": "中共党史党建学的本体论、认识论和方法论.txt"
    },
    {
        "id": "identity_26",
        "conversations": [
            {
                "from": "user",
                "value": "在党政要闻中，党务工作理论与实践的研究内容有哪些？"
            },
            {
                "from": "assistant",
                "value": "党务工作理论与实践的研究内容包括基本问题、基本方法、基本经验和基本规律。"
            }
        ],
        "fact": "党务工作理论与实践旨在研究党务工作理论与实践的基本问题，研究党务工作的基本方法，总结党务工作的基本经验，揭示党务工作的基本规律。",
        "file_name": "中共党史党建学的本体论、认识论和方法论.txt"
    },
    {
        "id": "identity_27",
        "conversations": [
            {
                "from": "user",
                "value": "请简述党务工作理论与实践的主要研究方向。"
            },
            {
                "from": "assistant",
                "value": "党务工作理论与实践主要研究其基本问题，探索基本方法，总结基本经验，揭示基本规律。"
            }
        ],
        "fact": "党务工作理论与实践旨在研究党务工作理论与实践的基本问题，研究党务工作的基本方法，总结党务工作的基本经验，揭示党务工作的基本规律。",
        "file_name": "中共党史党建学的本体论、认识论和方法论.txt"
    },
    {
        "id": "identity_28",
        "conversations": [
            {
                "from": "user",
                "value": "如何理解党务工作理论与实践的研究目标？"
            },
            {
                "from": "assistant",
                "value": "党务工作理论与实践旨在深入研究相关问题，优化工作方法，提炼实践经验，把握内在规律。"
            }
        ],
        "fact": "党务工作理论与实践旨在研究党务工作理论与实践的基本问题，研究党务工作的基本方法，总结党务工作的基本经验，揭示党务工作的基本规律。",
        "file_name": "中共党史党建学的本体论、认识论和方法论.txt"
    },
    {
        "id": "identity_29",
        "conversations": [
            {
                "from": "user",
                "value": "在党政要闻中，党务工作理论与实践的研究内容有哪些？"
            },
            {
                "from": "assistant",
                "value": "党务工作理论与实践的研究内容包括基本问题、基本方法、基本经验和基本规律。"
            }
        ],
        "fact": "党务工作理论与实践旨在研究党务工作理论与实践的基本问题，研究党务工作的基本方法，总结党务工作的基本经验，揭示党务工作的基本规律。",
        "file_name": "中共党史党建学的本体论、认识论和方法论.txt"
    },
    {
        "id": "identity_30",
        "conversations": [
            {
                "from": "user",
                "value": "请简述党务工作理论与实践的主要研究方向。"
            },
            {
                "from": "assistant",
                "value": "党务工作理论与实践主要研究其基本问题，探索基本方法，总结基本经验，揭示基本规律。"
            }
        ],
        "fact": "党务工作理论与实践旨在研究党务工作理论与实践的基本问题，研究党务工作的基本方法，总结党务工作的基本经验，揭示党务工作的基本规律。",
        "file_name": "中共党史党建学的本体论、认识论和方法论.txt"
    },
    {
        "id": "identity_31",
        "conversations": [
            {
                "from": "user",
                "value": "党务工作理论与实践的研究领域涵盖了哪些方面？"
            },
            {
                "from": "assistant",
                "value": "党务工作理论与实践的研究领域包括其基础问题、方法论、实践经验和运行规律等方面。"
            }
        ],
        "fact": "党务工作理论与实践旨在研究党务工作理论与实践的基本问题，研究党务工作的基本方法，总结党务工作的基本经验，揭示党务工作的基本规律。",
        "file_name": "中共党史党建学的本体论、认识论和方法论.txt"
    },
    {
        "id": "identity_32",
        "conversations": [
            {
                "from": "user",
                "value": "请问党务工作理论与实践的研究内容主要包括哪些方面？"
            },
            {
                "from": "assistant",
                "value": "党务工作理论与实践主要研究党务工作的基本问题，包括基本方法、经验总结以及规律揭示等方面。"
            }
        ],
        "fact": "党务工作理论与实践旨在研究党务工作理论与实践的基本问题，研究党务工作的基本方法，总结党务工作的基本经验，揭示党务工作的基本规律。",
        "file_name": "中共党史党建学的本体论、认识论和方法论.txt"
    },
    {
        "id": "identity_33",
        "conversations": [
            {
                "from": "user",
                "value": "能否详细说明一下党务工作理论与实践的研究重点是什么？"
            },
            {
                "from": "assistant",
                "value": "研究重点主要包括对党务工作基本问题的探讨、基本方法的分析、基本经验的总结以及基本规律的揭示。"
            }
        ],
        "fact": "党务工作理论与实践旨在研究党务工作理论与实践的基本问题，研究党务工作的基本方法，总结党务工作的基本经验，揭示党务工作的基本规律。",
        "file_name": "中共党史党建学的本体论、认识论和方法论.txt"
    },
    {
        "id": "identity_34",
        "conversations": [
            {
                "from": "user",
                "value": "请问在研究党务工作理论与实践时，主要涉及哪些领域？"
            },
            {
                "from": "assistant",
                "value": "主要涉及对党务工作的理论和实践进行深入研究，涵盖了方法探索、经验总结和规律发现等多个领域。"
            }
        ],
        "fact": "党务工作理论与实践旨在研究党务工作理论与实践的基本问题，研究党务工作的基本方法，总结党务工作的基本经验，揭示党务工作的基本规律。",
        "file_name": "中共党史党建学的本体论、认识论和方法论.txt"
    },
    {
        "id": "identity_35",
        "conversations": [
            {
                "from": "user",
                "value": "能否简要介绍一下党务工作理论与实践的主要研究方向有哪些？"
            },
            {
                "from": "assistant",
                "value": "主要研究方向包括对党务工作中的基本问题进行研究，探索有效的工作方法，总结实践经验，并揭示其中蕴含的基本规律。"
            }
        ],
        "fact": "党务工作理论与实践旨在研究党务工作理论与实践的基本问题，研究党务工作的基本方法，总结党务工作的基本经验，揭示党务工作的基本规律。",
        "file_name": "中共党史党建学的本体论、认识论和方法论.txt"
    },
    {
        "id": "identity_36",
        "conversations": [
            {
                "from": "user",
                "value": "在当前的党政要闻中，对于中共党史党建学理论的学科属性和研究内容，有没有形成统一的认识？"
            },
            {
                "from": "assistant",
                "value": "目前，学界对于中共党史党建学理论的学科属性和研究内容仍有不同的认识。"
            }
        ],
        "fact": "作为新设置的学科方向，学界对于中共党史党建学理论的学科属性和研究内容仍有不同的认识。",
        "file_name": "中共党史党建学的本体论、认识论和方法论.txt"
    },
    {
        "id": "identity_37",
        "conversations": [
            {
                "from": "user",
                "value": "在你所了解的党政要闻中，关于中共党史党建学理论的研究进展如何？"
            },
            {
                "from": "assistant",
                "value": "据我所知，虽然该学科方向较新，但学界对其学科属性和研究内容已展开积极探讨。"
            }
        ],
        "fact": "作为新设置的学科方向，学界对于中共党史党建学理论的学科属性和研究内容仍有不同的认识。",
        "file_name": "中共党史党建学的本体论、认识论和方法论.txt"
    },
    {
        "id": "identity_38",
        "conversations": [
            {
                "from": "user",
                "value": "在探讨中共党史党建学理论的学科属性和研究内容时，学术界是否存在共识？"
            },
            {
                "from": "assistant",
                "value": "目前，学术界对于中共党史党建学理论的学科属性和研究内容尚未达成一致。"
            }
        ],
        "fact": "作为新设置的学科方向，学界对于中共党史党建学理论的学科属性和研究内容仍有不同的认识。",
        "file_name": "中共党史党建学的本体论、认识论和方法论.txt"
    },
    {
        "id": "identity_39",
        "conversations": [
            {
                "from": "user",
                "value": "关于中共党史党建学理论的学科定位与研究方向，专家学者们的观点是否趋同？"
            },
            {
                "from": "assistant",
                "value": "专家学者们对中共党史党建学理论的学科定位与研究方向持有不同观点。"
            }
        ],
        "fact": "作为新设置的学科方向，学界对于中共党史党建学理论的学科属性和研究内容仍有不同的认识。",
        "file_name": "中共党史党建学的本体论、认识论和方法论.txt"
    },
    {
        "id": "identity_40",
        "conversations": [
            {
                "from": "user",
                "value": "在研究中共党史与党的建设学说的过程中，研究者们的侧重点是否有所差异？"
            },
            {
                "from": "assistant",
                "value": "是的，研究者们在研究中共党史与党的建设学说时，侧重点有所不同。"
            }
        ],
        "fact": "作为新设置的学科方向，学界对于中共党史党建学理论的学科属性和研究内容仍有不同的认识。",
        "file_name": "中共党史党建学的本体论、认识论和方法论.txt"
    },
    {
        "id": "identity_41",
        "conversations": [
            {
                "from": "user",
                "value": "能否简要介绍一下中共党史党建学理论的学科属性和研究内容？"
            },
            {
                "from": "assistant",
                "value": "中共党史党建学理论是一门研究中国共产党历史和党的建设的学科，主要涵盖了党的历史发展、组织建设、思想建设、作风建设等方面。然而，对于该学科的具体属性和研究内容，学界目前还没有形成统一的认识。"
            }
        ],
        "fact": "作为新设置的学科方向，学界对于中共党史党建学理论的学科属性和研究内容仍有不同的认识。",
        "file_name": "中共党史党建学的本体论、认识论和方法论.txt"
    },
    {
        "id": "identity_42",
        "conversations": [
            {
                "from": "user",
                "value": "请问中共党史党建学理论的研究对象是什么？"
            },
            {
                "from": "assistant",
                "value": "中共党史党建学理论的研究对象主要是中国共产党的历史发展和党的建设实践，包括党的指导思想、组织结构、领导体制等方面的内容。然而，对于该学科的具体研究对象，学界目前还没有形成统一的认识。"
            }
        ],
        "fact": "作为新设置的学科方向，学界对于中共党史党建学理论的学科属性和研究内容仍有不同的认识。",
        "file_name": "中共党史党建学的本体论、认识论和方法论.txt"
    },
    {
        "id": "identity_43",
        "conversations": [
            {
                "from": "user",
                "value": "能否举例说明一下中共党史党建学研究的具体内容？"
            },
            {
                "from": "assistant",
                "value": "当然可以。例如，中共党史的研究内容包括中国共产党的成立、发展历程以及在不同历史时期的重要事件和决策等；而党的建设的研究内容包括党的组织结构、干部队伍建设、作风建设等方面的理论和实践探索等。然而，对于该学科的具体研究内容，学界目前还没有形成统一的认识。"
            }
        ],
        "fact": "作为新设置的学科方向，学界对于中共党史党建学理论的学科属性和研究内容仍有不同的认识。",
        "file_name": "中共党史党建学的本体论、认识论和方法论.txt"
    },
    {
        "id": "identity_0",
        "conversations": [
            {
                "from": "user",
                "value": "近期，甘肃省委组织部有何重要举措？"
            },
            {
                "from": "assistant",
                "value": "近期，中共甘肃省委组织部发布了干部任前公示的公告。"
            }
        ],
        "fact": "中共甘肃省委组织部发布了干部任前公示的公告。",
        "file_name": "中共甘肃省委组织部关于干部任前公示的公告.txt"
    },
    {
        "id": "identity_1",
        "conversations": [
            {
                "from": "user",
                "value": "请问甘肃省委组织部最近有何动态？"
            },
            {
                "from": "assistant",
                "value": "最近，中共甘肃省委组织部发布了干部任前公示的公告。"
            }
        ],
        "fact": "中共甘肃省委组织部发布了干部任前公示的公告。",
        "file_name": "中共甘肃省委组织部关于干部任前公示的公告.txt"
    },
    {
        "id": "identity_2",
        "conversations": [
            {
                "from": "user",
                "value": "据了解，甘肃省委组织部近期有何新动作？"
            },
            {
                "from": "assistant",
                "value": "据了解，中共甘肃省委组织部近期发布了干部任前公示的公告。"
            }
        ],
        "fact": "中共甘肃省委组织部发布了干部任前公示的公告。",
        "file_name": "中共甘肃省委组织部关于干部任前公示的公告.txt"
    },
    {
        "id": "identity_3",
        "conversations": [
            {
                "from": "user",
                "value": "近期，中共甘肃省委组织部有何重要举措？"
            },
            {
                "from": "assistant",
                "value": "近期，中共甘肃省委组织部发布了干部任前公示的公告。"
            }
        ],
        "fact": "中共甘肃省委组织部发布了干部任前公示的公告。",
        "file_name": "中共甘肃省委组织部关于干部任前公示的公告.txt"
    },
    {
        "id": "identity_4",
        "conversations": [
            {
                "from": "user",
                "value": "请问中共甘肃省委组织部最近有何动态？"
            },
            {
                "from": "assistant",
                "value": "中共甘肃省委组织部最近发布了干部任前公示的公告。"
            }
        ],
        "fact": "中共甘肃省委组织部发布了干部任前公示的公告。",
        "file_name": "中共甘肃省委组织部关于干部任前公示的公告.txt"
    },
    {
        "id": "identity_5",
        "conversations": [
            {
                "from": "user",
                "value": "据了解，中共甘肃省委组织部近期有何动作？"
            },
            {
                "from": "assistant",
                "value": "据了解，中共甘肃省委组织部近期发布了干部任前公示的公告。"
            }
        ],
        "fact": "中共甘肃省委组织部发布了干部任前公示的公告。",
        "file_name": "中共甘肃省委组织部关于干部任前公示的公告.txt"
    },
    {
        "id": "identity_6",
        "conversations": [
            {
                "from": "user",
                "value": "近期，中共甘肃省委组织部有何重要举措？"
            },
            {
                "from": "assistant",
                "value": "近期，中共甘肃省委组织部发布了干部任前公示的公告。"
            }
        ],
        "fact": "中共甘肃省委组织部发布了干部任前公示的公告。",
        "file_name": "中共甘肃省委组织部关于干部任前公示的公告.txt"
    },
    {
        "id": "identity_7",
        "conversations": [
            {
                "from": "user",
                "value": "请问中共甘肃省委组织部最近是否有发布任何公告？"
            },
            {
                "from": "assistant",
                "value": "是的，中共甘肃省委组织部最近发布了干部任前公示的公告。"
            }
        ],
        "fact": "中共甘肃省委组织部发布了干部任前公示的公告。",
        "file_name": "中共甘肃省委组织部关于干部任前公示的公告.txt"
    },
    {
        "id": "identity_8",
        "conversations": [
            {
                "from": "user",
                "value": "据了解，中共甘肃省委组织部近期有一项重要工作，请问是什么？"
            },
            {
                "from": "assistant",
                "value": "据了解，中共甘肃省委组织部近期的重要工作是发布干部任前公示的公告。"
            }
        ],
        "fact": "中共甘肃省委组织部发布了干部任前公示的公告。",
        "file_name": "中共甘肃省委组织部关于干部任前公示的公告.txt"
    },
    {
        "id": "identity_9",
        "conversations": [
            {
                "from": "user",
                "value": "能否透露一下中共甘肃省委组织部最近的工作动态？"
            },
            {
                "from": "assistant",
                "value": "当然可以，根据我所了解的信息，中共甘肃省委组织部最近的工作动态是发布了干部任前公示的公告。"
            }
        ],
        "fact": "中共甘肃省委组织部发布了干部任前公示的公告。",
        "file_name": "中共甘肃省委组织部关于干部任前公示的公告.txt"
    },
    {
        "id": "identity_10",
        "conversations": [
            {
                "from": "user",
                "value": "请问，在近期的公示中，有哪些干部被拟进一步使用？"
            },
            {
                "from": "assistant",
                "value": "根据公示结果，马诚明、王宏林、王海青和张亮这几位干部被拟进一步使用。"
            }
        ],
        "fact": "马诚明、王宏林、王海青和张亮是拟进一步使用的公示对象。",
        "file_name": "中共甘肃省委组织部关于干部任前公示的公告.txt"
    },
    {
        "id": "identity_11",
        "conversations": [
            {
                "from": "user",
                "value": "能否告知我们，最近公示的拟进一步使用的干部名单中有哪些人？"
            },
            {
                "from": "assistant",
                "value": "根据公示信息，马诚明、王宏林、王海青和张亮是此次拟进一步使用的干部人选。"
            }
        ],
        "fact": "马诚明、王宏林、王海青和张亮是拟进一步使用的公示对象。",
        "file_name": "中共甘肃省委组织部关于干部任前公示的公告.txt"
    },
    {
        "id": "identity_12",
        "conversations": [
            {
                "from": "user",
                "value": "请问在最近的公示中，有哪几位干部被列入了拟进一步使用的名单？"
            },
            {
                "from": "assistant",
                "value": "根据相关公示内容，马诚明、王宏林、王海青和张亮这几位干部被列入了拟进一步使用的名单。"
            }
        ],
        "fact": "马诚明、王宏林、王海青和张亮是拟进一步使用的公示对象。",
        "file_name": "中共甘肃省委组织部关于干部任前公示的公告.txt"
    },
    {
        "id": "identity_13",
        "conversations": [
            {
                "from": "user",
                "value": "请问在近期的党政要闻中，有哪些干部被公示为拟进一步使用的对象？"
            },
            {
                "from": "assistant",
                "value": "根据最新的党政要闻，马诚明、王宏林、王海青和张亮这几位干部被公示为拟进一步使用的对象。"
            }
        ],
        "fact": "马诚明、王宏林、王海青和张亮是拟进一步使用的公示对象。",
        "file_name": "中共甘肃省委组织部关于干部任前公示的公告.txt"
    },
    {
        "id": "identity_14",
        "conversations": [
            {
                "from": "user",
                "value": "在最近的干部任免动态中，有哪些人被列入了拟提拔使用的名单？"
            },
            {
                "from": "assistant",
                "value": "根据相关信息，马诚明、王宏林、王海青和张亮这几位同志被列入了拟提拔使用的名单。"
            }
        ],
        "fact": "马诚明、王宏林、王海青和张亮是拟进一步使用的公示对象。",
        "file_name": "中共甘肃省委组织部关于干部任前公示的公告.txt"
    },
    {
        "id": "identity_15",
        "conversations": [
            {
                "from": "user",
                "value": "近期有哪些领导干部的人事变动引起了广泛关注？"
            },
            {
                "from": "assistant",
                "value": "近期，马诚明、王宏林、王海青和张亮这几位领导干部的人事变动引起了广泛关注。"
            }
        ],
        "fact": "马诚明、王宏林、王海青和张亮是拟进一步使用的公示对象。",
        "file_name": "中共甘肃省委组织部关于干部任前公示的公告.txt"
    },
    {
        "id": "identity_16",
        "conversations": [
            {
                "from": "user",
                "value": "请问，在近期的公示中，有哪些干部被拟进一步使用？"
            },
            {
                "from": "assistant",
                "value": "马诚明、王宏林、王海青和张亮是拟进一步使用的公示对象。"
            }
        ],
        "fact": "马诚明、王宏林、王海青和张亮是拟进一步使用的公示对象。",
        "file_name": "中共甘肃省委组织部关于干部任前公示的公告.txt"
    },
    {
        "id": "identity_17",
        "conversations": [
            {
                "from": "user",
                "value": "能否透露一下，最近有哪些干部被列入了拟进一步使用的名单？"
            },
            {
                "from": "assistant",
                "value": "根据公示信息，马诚明、王宏林、王海青和张亮是拟进一步使用的公示对象。"
            }
        ],
        "fact": "马诚明、王宏林、王海青和张亮是拟进一步使用的公示对象。",
        "file_name": "中共甘肃省委组织部关于干部任前公示的公告.txt"
    },
    {
        "id": "identity_18",
        "conversations": [
            {
                "from": "user",
                "value": "请问在最新的干部任用公示中，有哪几位干部被提名为拟进一步使用的对象？"
            },
            {
                "from": "assistant",
                "value": "根据相关公告，马诚明、王宏林、王海青和张亮是此次拟进一步使用的公示对象。"
            }
        ],
        "fact": "马诚明、王宏林、王海青和张亮是拟进一步使用的公示对象。",
        "file_name": "中共甘肃省委组织部关于干部任前公示的公告.txt"
    },
    {
        "id": "identity_19",
        "conversations": [
            {
                "from": "user",
                "value": "近期的党政要闻中提到了几位被提名为拟进一步使用的对象，请问他们的名字是什么？"
            },
            {
                "from": "assistant",
                "value": "根据相关报道，马诚明、王宏林、王海青和张亮是此次被提名为拟进一步使用的对象。"
            }
        ],
        "fact": "马诚明、王宏林、王海青和张亮是拟进一步使用的公示对象。",
        "file_name": "中共甘肃省委组织部关于干部任前公示的公告.txt"
    },
    {
        "id": "identity_20",
        "conversations": [
            {
                "from": "user",
                "value": "请问马诚明同志的职务是什么？"
            },
            {
                "from": "assistant",
                "value": "马诚明同志现任卓尼县委副书记、县长、二级巡视员。"
            }
        ],
        "fact": "马诚明是藏族，1973年3月生，现任卓尼县委副书记、县长、二级巡视员，拟任县（区）委书记。",
        "file_name": "中共甘肃省委组织部关于干部任前公示的公告.txt"
    },
    {
        "id": "identity_21",
        "conversations": [
            {
                "from": "user",
                "value": "能否介绍一下马诚明同志的基本情况？"
            },
            {
                "from": "assistant",
                "value": "当然可以，马诚明同志是藏族，1973年3月生，现任卓尼县委副书记、县长、二级巡视员。他工作能力强，政治素质高，拟任县（区）委书记。"
            }
        ],
        "fact": "马诚明是藏族，1973年3月生，现任卓尼县委副书记、县长、二级巡视员，拟任县（区）委书记。",
        "file_name": "中共甘肃省委组织部关于干部任前公示的公告.txt"
    },
    {
        "id": "identity_22",
        "conversations": [
            {
                "from": "user",
                "value": "请问马诚明的职务是什么？"
            },
            {
                "from": "assistant",
                "value": "马诚明现任卓尼县委副书记、县长、二级巡视员。"
            }
        ],
        "fact": "马诚明是藏族，1973年3月生，现任卓尼县委副书记、县长、二级巡视员，拟任县（区）委书记。",
        "file_name": "中共甘肃省委组织部关于干部任前公示的公告.txt"
    },
    {
        "id": "identity_23",
        "conversations": [
            {
                "from": "user",
                "value": "马诚明的民族和出生年月是什么？"
            },
            {
                "from": "assistant",
                "value": "马诚明是藏族，出生于1973年3月。"
            }
        ],
        "fact": "马诚明是藏族，1973年3月生，现任卓尼县委副书记、县长、二级巡视员，拟任县（区）委书记。",
        "file_name": "中共甘肃省委组织部关于干部任前公示的公告.txt"
    },
    {
        "id": "identity_24",
        "conversations": [
            {
                "from": "user",
                "value": "请问马诚明拟任的职务是什么？"
            },
            {
                "from": "assistant",
                "value": "马诚明拟任县（区）委书记。"
            }
        ],
        "fact": "马诚明是藏族，1973年3月生，现任卓尼县委副书记、县长、二级巡视员，拟任县（区）委书记。",
        "file_name": "中共甘肃省委组织部关于干部任前公示的公告.txt"
    },
    {
        "id": "identity_25",
        "conversations": [
            {
                "from": "user",
                "value": "请问马诚明的职务是什么？"
            },
            {
                "from": "assistant",
                "value": "马诚明现任卓尼县委副书记、县长、二级巡视员。"
            }
        ],
        "fact": "马诚明是藏族，1973年3月生，现任卓尼县委副书记、县长、二级巡视员，拟任县（区）委书记。",
        "file_name": "中共甘肃省委组织部关于干部任前公示的公告.txt"
    },
    {
        "id": "identity_26",
        "conversations": [
            {
                "from": "user",
                "value": "能否介绍一下马诚明的基本情况？"
            },
            {
                "from": "assistant",
                "value": "马诚明是藏族，1973年3月生，现任卓尼县委副书记、县长、二级巡视员，拟任县（区）委书记。"
            }
        ],
        "fact": "马诚明是藏族，1973年3月生，现任卓尼县委副书记、县长、二级巡视员，拟任县（区）委书记。",
        "file_name": "中共甘肃省委组织部关于干部任前公示的公告.txt"
    },
    {
        "id": "identity_27",
        "conversations": [
            {
                "from": "user",
                "value": "请问马诚明的职务有哪些变化？"
            },
            {
                "from": "assistant",
                "value": "马诚明现任卓尼县委副书记、县长、二级巡视员，拟任县（区）委书记。"
            }
        ],
        "fact": "马诚明是藏族，1973年3月生，现任卓尼县委副书记、县长、二级巡视员，拟任县（区）委书记。",
        "file_name": "中共甘肃省委组织部关于干部任前公示的公告.txt"
    },
    {
        "id": "identity_28",
        "conversations": [
            {
                "from": "user",
                "value": "关于马诚明的职务变动有何消息？"
            },
            {
                "from": "assistant",
                "value": "据了解，马诚明拟任县（区）委书记。"
            }
        ],
        "fact": "马诚明是藏族，1973年3月生，现任卓尼县委副书记、县长、二级巡视员，拟任县（区）委书记。",
        "file_name": "中共甘肃省委组织部关于干部任前公示的公告.txt"
    },
    {
        "id": "identity_29",
        "conversations": [
            {
                "from": "user",
                "value": "请问王宏林副部长的职务有哪些？"
            },
            {
                "from": "assistant",
                "value": "王宏林副部长现任甘南州委宣传部副部长、甘南州融媒体中心党组书记、主任（总编辑）。"
            }
        ],
        "fact": "王宏林是汉族，1980年2月生，现任甘南州委宣传部副部长、甘南州融媒体中心党组书记、主任（总编辑），拟提名为县（区）长候选人。",
        "file_name": "中共甘肃省委组织部关于干部任前公示的公告.txt"
    },
    {
        "id": "identity_30",
        "conversations": [
            {
                "from": "user",
                "value": "能否介绍一下王宏林副部长的工作经历？"
            },
            {
                "from": "assistant",
                "value": "王宏林副部长是汉族，1980年2月生，他现任甘南州委宣传部副部长、甘南州融媒体中心党组书记、主任（总编辑），并且拟提名为县（区）长候选人。"
            }
        ],
        "fact": "王宏林是汉族，1980年2月生，现任甘南州委宣传部副部长、甘南州融媒体中心党组书记、主任（总编辑），拟提名为县（区）长候选人。",
        "file_name": "中共甘肃省委组织部关于干部任前公示的公告.txt"
    },
    {
        "id": "identity_31",
        "conversations": [
            {
                "from": "user",
                "value": "请问王宏林先生目前担任什么职务？"
            },
            {
                "from": "assistant",
                "value": "王宏林先生现任甘南州委宣传部副部长、甘南州融媒体中心党组书记、主任（总编辑）。"
            }
        ],
        "fact": "王宏林是汉族，1980年2月生，现任甘南州委宣传部副部长、甘南州融媒体中心党组书记、主任（总编辑），拟提名为县（区）长候选人。",
        "file_name": "中共甘肃省委组织部关于干部任前公示的公告.txt"
    },
    {
        "id": "identity_32",
        "conversations": [
            {
                "from": "user",
                "value": "能否介绍一下王宏林先生的背景信息？"
            },
            {
                "from": "assistant",
                "value": "王宏林先生是汉族，出生于1980年2月，他现任甘南州委宣传部副部长、甘南州融媒体中心党组书记、主任（总编辑），并且拟提名为县（区）长候选人。"
            }
        ],
        "fact": "王宏林是汉族，1980年2月生，现任甘南州委宣传部副部长、甘南州融媒体中心党组书记、主任（总编辑），拟提名为县（区）长候选人。",
        "file_name": "中共甘肃省委组织部关于干部任前公示的公告.txt"
    },
    {
        "id": "identity_33",
        "conversations": [
            {
                "from": "user",
                "value": "请问王宏林先生在党政宣传领域有何重要职责？"
            },
            {
                "from": "assistant",
                "value": "作为甘南州委宣传部副部长和融媒体中心党组书记、主任（总编辑），王宏林先生在党政宣传领域承担着重要的领导和决策职责。"
            }
        ],
        "fact": "王宏林是汉族，1980年2月生，现任甘南州委宣传部副部长、甘南州融媒体中心党组书记、主任（总编辑），拟提名为县（区）长候选人。",
        "file_name": "中共甘肃省委组织部关于干部任前公示的公告.txt"
    },
    {
        "id": "identity_34",
        "conversations": [
            {
                "from": "user",
                "value": "请问王宏林先生的职务是什么？"
            },
            {
                "from": "assistant",
                "value": "王宏林先生现任甘南州委宣传部副部长、甘南州融媒体中心党组书记、主任（总编辑）。"
            }
        ],
        "fact": "王宏林是汉族，1980年2月生，现任甘南州委宣传部副部长、甘南州融媒体中心党组书记、主任（总编辑），拟提名为县（区）长候选人。",
        "file_name": "中共甘肃省委组织部关于干部任前公示的公告.txt"
    },
    {
        "id": "identity_35",
        "conversations": [
            {
                "from": "user",
                "value": "能否介绍一下王宏林先生的职务信息？"
            },
            {
                "from": "assistant",
                "value": "当然，王宏林先生现任甘南州委宣传部副部长、甘南州融媒体中心党组书记、主任（总编辑）。"
            }
        ],
        "fact": "王宏林是汉族，1980年2月生，现任甘南州委宣传部副部长、甘南州融媒体中心党组书记、主任（总编辑），拟提名为县（区）长候选人。",
        "file_name": "中共甘肃省委组织部关于干部任前公示的公告.txt"
    },
    {
        "id": "identity_36",
        "conversations": [
            {
                "from": "user",
                "value": "请问您对王宏林先生的职务了解吗？"
            },
            {
                "from": "assistant",
                "value": "是的，我了解到王宏林先生现任甘南州委宣传部副部长、甘南州融媒体中心党组书记、主任（总编辑）。"
            }
        ],
        "fact": "王宏林是汉族，1980年2月生，现任甘南州委宣传部副部长、甘南州融媒体中心党组书记、主任（总编辑），拟提名为县（区）长候选人。",
        "file_name": "中共甘肃省委组织部关于干部任前公示的公告.txt"
    },
    {
        "id": "identity_37",
        "conversations": [
            {
                "from": "user",
                "value": "关于王宏林先生的职务，您有什么可以分享的信息吗？"
            },
            {
                "from": "assistant",
                "value": "我可以告诉您的是，王宏林先生现任甘南州委宣传部副部长、甘南州融媒体中心党组书记、主任（总编辑）。"
            }
        ],
        "fact": "王宏林是汉族，1980年2月生，现任甘南州委宣传部副部长、甘南州融媒体中心党组书记、主任（总编辑），拟提名为县（区）长候选人。",
        "file_name": "中共甘肃省委组织部关于干部任前公示的公告.txt"
    },
    {
        "id": "identity_38",
        "conversations": [
            {
                "from": "user",
                "value": "请问王海青先生的职务是什么？"
            },
            {
                "from": "assistant",
                "value": "王海青先生现任甘南州工业和信息化局党组书记、局长。"
            }
        ],
        "fact": "王海青是藏族，1983年10月生，现任甘南州工业和信息化局党组书记、局长，拟提名为县（区）长候选人。",
        "file_name": "中共甘肃省委组织部关于干部任前公示的公告.txt"
    },
    {
        "id": "identity_39",
        "conversations": [
            {
                "from": "user",
                "value": "能否介绍一下王海青先生的工作经历？"
            },
            {
                "from": "assistant",
                "value": "当然可以，王海青先生是藏族，1983年10月生，他现任甘南州工业和信息化局党组书记、局长，并且拟提名为县（区）长候选人。"
            }
        ],
        "fact": "王海青是藏族，1983年10月生，现任甘南州工业和信息化局党组书记、局长，拟提名为县（区）长候选人。",
        "file_name": "中共甘肃省委组织部关于干部任前公示的公告.txt"
    },
    {
        "id": "identity_40",
        "conversations": [
            {
                "from": "user",
                "value": "请问王海青先生目前担任什么职务？"
            },
            {
                "from": "assistant",
                "value": "王海青先生现任甘南州工业和信息化局党组书记、局长。"
            }
        ],
        "fact": "王海青是藏族，1983年10月生，现任甘南州工业和信息化局党组书记、局长，拟提名为县（区）长候选人。",
        "file_name": "中共甘肃省委组织部关于干部任前公示的公告.txt"
    },
    {
        "id": "identity_41",
        "conversations": [
            {
                "from": "user",
                "value": "能否介绍一下王海青先生的民族和出生年月？"
            },
            {
                "from": "assistant",
                "value": "王海青先生是藏族，出生于1983年10月。"
            }
        ],
        "fact": "王海青是藏族，1983年10月生，现任甘南州工业和信息化局党组书记、局长，拟提名为县（区）长候选人。",
        "file_name": "中共甘肃省委组织部关于干部任前公示的公告.txt"
    },
    {
        "id": "identity_42",
        "conversations": [
            {
                "from": "user",
                "value": "请问王海青先生目前担任什么职务？"
            },
            {
                "from": "assistant",
                "value": "王海青先生现任甘南州工业和信息化局党组书记、局长。"
            }
        ],
        "fact": "王海青是藏族，1983年10月生，现任甘南州工业和信息化局党组书记、局长，拟提名为县（区）长候选人。",
        "file_name": "中共甘肃省委组织部关于干部任前公示的公告.txt"
    },
    {
        "id": "identity_43",
        "conversations": [
            {
                "from": "user",
                "value": "能否介绍一下王海青先生的民族和出生年月？"
            },
            {
                "from": "assistant",
                "value": "王海青先生是藏族，出生于1983年10月。"
            }
        ],
        "fact": "王海青是藏族，1983年10月生，现任甘南州工业和信息化局党组书记、局长，拟提名为县（区）长候选人。",
        "file_name": "中共甘肃省委组织部关于干部任前公示的公告.txt"
    },
    {
        "id": "identity_44",
        "conversations": [
            {
                "from": "user",
                "value": "请问拟提名的职位是什么？"
            },
            {
                "from": "assistant",
                "value": "拟提名为县（区）长候选人。"
            }
        ],
        "fact": "王海青是藏族，1983年10月生，现任甘南州工业和信息化局党组书记、局长，拟提名为县（区）长候选人。",
        "file_name": "中共甘肃省委组织部关于干部任前公示的公告.txt"
    },
    {
        "id": "identity_45",
        "conversations": [
            {
                "from": "user",
                "value": "请问张亮同志的职务是什么？"
            },
            {
                "from": "assistant",
                "value": "张亮同志现任甘南州发展和改革委员会党组书记、主任。"
            }
        ],
        "fact": "张亮是汉族，1983年6月生，法学学士，现任甘南州发展和改革委员会党组书记、主任，拟任县（区）委书记。",
        "file_name": "中共甘肃省委组织部关于干部任前公示的公告.txt"
    },
    {
        "id": "identity_46",
        "conversations": [
            {
                "from": "user",
                "value": "能否介绍一下张亮同志的工作履历？"
            },
            {
                "from": "assistant",
                "value": "张亮同志是汉族，1983年6月生，法学学士，现任甘南州发展和改革委员会党组书记、主任，拟任县（区）委书记。"
            }
        ],
        "fact": "张亮是汉族，1983年6月生，法学学士，现任甘南州发展和改革委员会党组书记、主任，拟任县（区）委书记。",
        "file_name": "中共甘肃省委组织部关于干部任前公示的公告.txt"
    },
    {
        "id": "identity_47",
        "conversations": [
            {
                "from": "user",
                "value": "请问张亮先生目前担任什么职务？"
            },
            {
                "from": "assistant",
                "value": "张亮先生现任甘南州发展和改革委员会党组书记、主任。"
            }
        ],
        "fact": "张亮是汉族，1983年6月生，法学学士，现任甘南州发展和改革委员会党组书记、主任，拟任县（区）委书记。",
        "file_name": "中共甘肃省委组织部关于干部任前公示的公告.txt"
    },
    {
        "id": "identity_48",
        "conversations": [
            {
                "from": "user",
                "value": "能否介绍一下张亮先生的背景信息？"
            },
            {
                "from": "assistant",
                "value": "张亮先生是汉族，1983年6月生，法学学士，现任甘南州发展和改革委员会党组书记、主任，拟任县（区）委书记。"
            }
        ],
        "fact": "张亮是汉族，1983年6月生，法学学士，现任甘南州发展和改革委员会党组书记、主任，拟任县（区）委书记。",
        "file_name": "中共甘肃省委组织部关于干部任前公示的公告.txt"
    },
    {
        "id": "identity_49",
        "conversations": [
            {
                "from": "user",
                "value": "请问张亮先生的职务是什么？"
            },
            {
                "from": "assistant",
                "value": "张亮先生现任甘南州发展和改革委员会党组书记、主任。"
            }
        ],
        "fact": "张亮是汉族，1983年6月生，法学学士，现任甘南州发展和改革委员会党组书记、主任，拟任县（区）委书记。",
        "file_name": "中共甘肃省委组织部关于干部任前公示的公告.txt"
    },
    {
        "id": "identity_50",
        "conversations": [
            {
                "from": "user",
                "value": "能否介绍一下张亮先生的职务信息？"
            },
            {
                "from": "assistant",
                "value": "当然，张亮先生现任甘南州发展和改革委员会党组书记、主任。"
            }
        ],
        "fact": "张亮是汉族，1983年6月生，法学学士，现任甘南州发展和改革委员会党组书记、主任，拟任县（区）委书记。",
        "file_name": "中共甘肃省委组织部关于干部任前公示的公告.txt"
    },
    {
        "id": "identity_51",
        "conversations": [
            {
                "from": "user",
                "value": "请问您了解张亮先生的职务情况吗？"
            },
            {
                "from": "assistant",
                "value": "是的，我了解到张亮先生现任甘南州发展和改革委员会党组书记、主任。"
            }
        ],
        "fact": "张亮是汉族，1983年6月生，法学学士，现任甘南州发展和改革委员会党组书记、主任，拟任县（区）委书记。",
        "file_name": "中共甘肃省委组织部关于干部任前公示的公告.txt"
    },
    {
        "id": "identity_52",
        "conversations": [
            {
                "from": "user",
                "value": "关于张亮先生的职务，您有什么可以分享的信息吗？"
            },
            {
                "from": "assistant",
                "value": "我可以告诉您的是，张亮先生现任甘南州发展和改革委员会党组书记、主任。"
            }
        ],
        "fact": "张亮是汉族，1983年6月生，法学学士，现任甘南州发展和改革委员会党组书记、主任，拟任县（区）委书记。",
        "file_name": "中共甘肃省委组织部关于干部任前公示的公告.txt"
    },
    {
        "id": "identity_53",
        "conversations": [
            {
                "from": "user",
                "value": "请问公示期的起止时间是如何安排的？"
            },
            {
                "from": "assistant",
                "value": "公示期将从2024年9月23日开始，至2024年9月27日结束。"
            }
        ],
        "fact": "公示时间为2024年9月23日至2024年9月27日。",
        "file_name": "中共甘肃省委组织部关于干部任前公示的公告.txt"
    },
    {
        "id": "identity_54",
        "conversations": [
            {
                "from": "user",
                "value": "能否告知一下公示的具体时间段？"
            },
            {
                "from": "assistant",
                "value": "当然可以，公示将在2024年9月23日至9月27日期间进行。"
            }
        ],
        "fact": "公示时间为2024年9月23日至2024年9月27日。",
        "file_name": "中共甘肃省委组织部关于干部任前公示的公告.txt"
    },
    {
        "id": "identity_55",
        "conversations": [
            {
                "from": "user",
                "value": "请问公示期的起止时间是如何规定的？"
            },
            {
                "from": "assistant",
                "value": "公示期的起止时间已明确规定为2024年9月23日至2024年9月27日。"
            }
        ],
        "fact": "公示时间为2024年9月23日至2024年9月27日。",
        "file_name": "中共甘肃省委组织部关于干部任前公示的公告.txt"
    },
    {
        "id": "identity_56",
        "conversations": [
            {
                "from": "user",
                "value": "能否具体说明一下公示期的时间范围？"
            },
            {
                "from": "assistant",
                "value": "当然，公示期的时间范围已经明确，即从2024年9月23日开始，至9月27日结束。"
            }
        ],
        "fact": "公示时间为2024年9月23日至2024年9月27日。",
        "file_name": "中共甘肃省委组织部关于干部任前公示的公告.txt"
    },
    {
        "id": "identity_57",
        "conversations": [
            {
                "from": "user",
                "value": "请问公示期的起止时间是哪天？"
            },
            {
                "from": "assistant",
                "value": "公示期从2024年9月23日开始，至2024年9月27日结束。"
            }
        ],
        "fact": "公示时间为2024年9月23日至2024年9月27日。",
        "file_name": "中共甘肃省委组织部关于干部任前公示的公告.txt"
    },
    {
        "id": "identity_58",
        "conversations": [
            {
                "from": "user",
                "value": "能否告知公示的具体时间段？"
            },
            {
                "from": "assistant",
                "value": "当然可以，公示将在2024年9月23日至9月27日期间进行。"
            }
        ],
        "fact": "公示时间为2024年9月23日至2024年9月27日。",
        "file_name": "中共甘肃省委组织部关于干部任前公示的公告.txt"
    },
    {
        "id": "identity_59",
        "conversations": [
            {
                "from": "user",
                "value": "请问我们能在何时看到相关公示信息？"
            },
            {
                "from": "assistant",
                "value": "您可以在2024年9月的第3周，即从9月第3个星期一开始到星期五期间查看相关公示信息。"
            }
        ],
        "fact": "公示时间为2024年9月23日至2024年9月27日。",
        "file_name": "中共甘肃省委组织部关于干部任前公示的公告.txt"
    },
    {
        "id": "identity_60",
        "conversations": [
            {
                "from": "user",
                "value": "请问党政要闻的受理时间是如何安排的？"
            },
            {
                "from": "assistant",
                "value": "我们的受理时间是每天上午8：30到12：00，下午2：30到6：00。"
            }
        ],
        "fact": "受理时间为每天上午：8：30—12：00；下午：2：30—6：00。",
        "file_name": "中共甘肃省委组织部关于干部任前公示的公告.txt"
    },
    {
        "id": "identity_61",
        "conversations": [
            {
                "from": "user",
                "value": "能否告知一下党政要闻的日常工作时间？"
            },
            {
                "from": "assistant",
                "value": "当然，我们的工作时间是每天上午8：30至12：00，下午2：30至6：00。"
            }
        ],
        "fact": "受理时间为每天上午：8：30—12：00；下午：2：30—6：00。",
        "file_name": "中共甘肃省委组织部关于干部任前公示的公告.txt"
    },
    {
        "id": "identity_62",
        "conversations": [
            {
                "from": "user",
                "value": "关于党政要闻的办公时间，您能具体说明一下吗？"
            },
            {
                "from": "assistant",
                "value": "我们的办公时间设定为每天上午8点半到12点，下午2点半到6点。"
            }
        ],
        "fact": "受理时间为每天上午：8：30—12：00；下午：2：30—6：00。",
        "file_name": "中共甘肃省委组织部关于干部任前公示的公告.txt"
    },
    {
        "id": "identity_63",
        "conversations": [
            {
                "from": "user",
                "value": "在党政要闻的受理时间内，我们能获取到哪些方面的信息？"
            },
            {
                "from": "assistant",
                "value": "在党政要闻的受理时间内，我们可以获取到有关国家政策、政府决策、重要会议等方面的信息。"
            }
        ],
        "fact": "受理时间为每天上午：8：30—12：00；下午：2：30—6：00。",
        "file_name": "中共甘肃省委组织部关于干部任前公示的公告.txt"
    },
    {
        "id": "identity_64",
        "conversations": [
            {
                "from": "user",
                "value": "如果错过了党政要闻的受理时间，还有其他途径获取相关信息吗？"
            },
            {
                "from": "assistant",
                "value": "如果错过了党政要闻的受理时间，可以通过新闻媒体、政府网站、新闻发布会等途径获取相关信息。"
            }
        ],
        "fact": "受理时间为每天上午：8：30—12：00；下午：2：30—6：00。",
        "file_name": "中共甘肃省委组织部关于干部任前公示的公告.txt"
    },
    {
        "id": "identity_65",
        "conversations": [
            {
                "from": "user",
                "value": "党政要闻的受理时间是否有季节性调整？"
            },
            {
                "from": "assistant",
                "value": "目前没有关于党政要闻受理时间季节性调整的信息。"
            }
        ],
        "fact": "受理时间为每天上午：8：30—12：00；下午：2：30—6：00。",
        "file_name": "中共甘肃省委组织部关于干部任前公示的公告.txt"
    },
    {
        "id": "identity_66",
        "conversations": [
            {
                "from": "user",
                "value": "请问党政要闻的受理时间是如何安排的？"
            },
            {
                "from": "assistant",
                "value": "党政要闻的受理时间是每天上午8：30到12：00，下午2：30到6：00。"
            }
        ],
        "fact": "受理时间为每天上午：8：30—12：00；下午：2：30—6：00。",
        "file_name": "中共甘肃省委组织部关于干部任前公示的公告.txt"
    },
    {
        "id": "identity_67",
        "conversations": [
            {
                "from": "user",
                "value": "能否告知一下党政要闻的每日工作时段？"
            },
            {
                "from": "assistant",
                "value": "当然可以，党政要闻的每日工作时段为上午8：30至12：00，下午2：30至6：00。"
            }
        ],
        "fact": "受理时间为每天上午：8：30—12：00；下午：2：30—6：00。",
        "file_name": "中共甘肃省委组织部关于干部任前公示的公告.txt"
    },
    {
        "id": "identity_68",
        "conversations": [
            {
                "from": "user",
                "value": "关于党政要闻的工作时间，您能具体说明一下吗？"
            },
            {
                "from": "assistant",
                "value": "没问题，党政要闻的工作时间是每天上午8点半到12点，下午2点半到6点。"
            }
        ],
        "fact": "受理时间为每天上午：8：30—12：00；下午：2：30—6：00。",
        "file_name": "中共甘肃省委组织部关于干部任前公示的公告.txt"
    },
    {
        "id": "identity_69",
        "conversations": [
            {
                "from": "user",
                "value": "请问，我们应该向哪个部门提交相关材料？"
            },
            {
                "from": "assistant",
                "value": "您可以向省委组织部干部监督处提交相关材料。"
            }
        ],
        "fact": "受理部门为省委组织部干部监督处。",
        "file_name": "中共甘肃省委组织部关于干部任前公示的公告.txt"
    },
    {
        "id": "identity_70",
        "conversations": [
            {
                "from": "user",
                "value": "在处理这类事务时，我们通常与哪个部门进行对接？"
            },
            {
                "from": "assistant",
                "value": "我们通常与省委组织部干部监督处进行对接。"
            }
        ],
        "fact": "受理部门为省委组织部干部监督处。",
        "file_name": "中共甘肃省委组织部关于干部任前公示的公告.txt"
    },
    {
        "id": "identity_71",
        "conversations": [
            {
                "from": "user",
                "value": "如果有任何疑问或需要进一步了解相关政策，我们应该咨询哪个部门？"
            },
            {
                "from": "assistant",
                "value": "您可以咨询省委组织部干部监督处以获取更详细的信息和政策解读。"
            }
        ],
        "fact": "受理部门为省委组织部干部监督处。",
        "file_name": "中共甘肃省委组织部关于干部任前公示的公告.txt"
    },
    {
        "id": "identity_72",
        "conversations": [
            {
                "from": "user",
                "value": "请问，对于党政要闻的受理部门是哪个？"
            },
            {
                "from": "assistant",
                "value": "根据相关信息，受理部门为省委组织部干部监督处。"
            }
        ],
        "fact": "受理部门为省委组织部干部监督处。",
        "file_name": "中共甘肃省委组织部关于干部任前公示的公告.txt"
    },
    {
        "id": "identity_73",
        "conversations": [
            {
                "from": "user",
                "value": "请问，对于相关问题的受理，具体是由哪个部门负责呢？"
            },
            {
                "from": "assistant",
                "value": "根据我了解的信息，受理部门是省委组织部干部监督处。"
            }
        ],
        "fact": "受理部门为省委组织部干部监督处。",
        "file_name": "中共甘肃省委组织部关于干部任前公示的公告.txt"
    },
    {
        "id": "identity_74",
        "conversations": [
            {
                "from": "user",
                "value": "能否告知一下，我们应该向哪个部门提交相关问题呢？"
            },
            {
                "from": "assistant",
                "value": "根据我所掌握的情况，您可以向省委组织部干部监督处提交相关问题。"
            }
        ],
        "fact": "受理部门为省委组织部干部监督处。",
        "file_name": "中共甘肃省委组织部关于干部任前公示的公告.txt"
    },
    {
        "id": "identity_75",
        "conversations": [
            {
                "from": "user",
                "value": "请问在处理这类问题上，有没有一个特定的部门来负责呢？"
            },
            {
                "from": "assistant",
                "value": "是的，根据我所知的信息来看，这个特定的部门就是省委组织部干部监督处。"
            }
        ],
        "fact": "受理部门为省委组织部干部监督处。",
        "file_name": "中共甘肃省委组织部关于干部任前公示的公告.txt"
    },
    {
        "id": "identity_76",
        "conversations": [
            {
                "from": "user",
                "value": "如果我们要咨询或反映相关问题的话，应该找哪个部门呢？"
            },
            {
                "from": "assistant",
                "value": "您可以联系省委组织部干部监督处进行咨询或反映问题。"
            }
        ],
        "fact": "受理部门为省委组织部干部监督处。",
        "file_name": "中共甘肃省委组织部关于干部任前公示的公告.txt"
    },
    {
        "id": "identity_77",
        "conversations": [
            {
                "from": "user",
                "value": "能否告知我党政要闻中有关举报的热线电话和短信号码？"
            },
            {
                "from": "assistant",
                "value": "当然可以，电话举报热线是0931—12380，而短信举报的号码则是13909312380和139。"
            }
        ],
        "fact": "电话举报号码为：0931—12380；短信举报号码为：13909312380和139",
        "file_name": "中共甘肃省委组织部关于干部任前公示的公告.txt"
    },
    {
        "id": "identity_78",
        "conversations": [
            {
                "from": "user",
                "value": "能否请您提供一下党政要闻中有关举报的电话和短信号码？"
            },
            {
                "from": "assistant",
                "value": "当然可以，电话举报号码为：0931—12380；短信举报号码为：13909312380和139。"
            }
        ],
        "fact": "电话举报号码为：0931—12380；短信举报号码为：13909312380和139",
        "file_name": "中共甘肃省委组织部关于干部任前公示的公告.txt"
    },
    {
        "id": "identity_79",
        "conversations": [
            {
                "from": "user",
                "value": "能否告知我党政要闻中有关举报的电话和短信号码？"
            },
            {
                "from": "assistant",
                "value": "当然可以，电话举报号码为：0931—12380；短信举报号码为：13909312380和139。"
            }
        ],
        "fact": "电话举报号码为：0931—12380；短信举报号码为：13909312380和139",
        "file_name": "中共甘肃省委组织部关于干部任前公示的公告.txt"
    }
]